setup.py
conda_list_all_envs/__init__.py
conda_list_all_envs/cli.py
conda_list_all_envs.egg-info/PKG-INFO
conda_list_all_envs.egg-info/SOURCES.txt
conda_list_all_envs.egg-info/dependency_links.txt
conda_list_all_envs.egg-info/entry_points.txt
conda_list_all_envs.egg-info/top_level.txt