Metadata-Version: 1.0
Name: conda-list-all-envs
Version: 0.2
Summary: A tool for finding all of the packages inside all enviornments
Home-page: UNKNOWN
Author: Samaksh Goyal
Author-email: mailsamakshgoyal@gmail.com
License: BSD
Platform: UNKNOWN
